{
 "actions": [], 
 "autoname": "naming_series:",
 "creation": "2013-05-21 16:16:04",
 "doctype": "DocType",
 "document_type": "Document",
 "show_name_in_global_search": 1, 
 "engine": "InnoDB",
 "is_submittable": 1,
 "field_order": [  
 ],
 "fields": [
    {
    "bold": 1,
    "fieldname": "naming_series",
    "fieldtype": "Select",
    "hide_days": 1,
    "hide_seconds": 1,
    "label": "Series",
    "no_copy": 1,
    "oldfieldname": "naming_series",
    "oldfieldtype": "Select",
    "options": "SRI-RET-.YYYY.-",
    "print_hide": 1,
    "reqd": 1,
    "set_only_once": 1
   },
   {
    "fieldname": "company",
    "fieldtype": "Link",
    "hide_days": 1,
    "hide_seconds": 1,
    "in_standard_filter": 1,
    "label": "Company",
    "oldfieldname": "company",
    "oldfieldtype": "Link",
    "options": "Company",
    "print_hide": 1,
    "remember_last_selected_value": 1,
    "reqd": 1
   },
   {
    "idx": 2,
    "name": "Purchase-Withholding-supplier",
    "parent": "Customize Form",
    "parentfield": "fields",
    "parenttype": "Customize Form",    
    "docstatus": 0,
    "label": "Proveedor",
    "fieldtype": "Link",
    "fieldname": "purchase_withholding_supplier",
    "non_negative": 0,
    "reqd": 0,
    "unique": 0,
    "in_list_view": 1,
    "in_standard_filter": 0,
    "in_global_search": 0,
    "in_preview": 0,
    "bold": 0,
    "allow_in_quick_entry": 0,
    "translatable": 1,
    "default": null,
    "precision": "",
    "length": 0,
    "options": "Supplier",
    "fetch_if_empty": 0,
    "permlevel": 0,
    "hidden": 0,
    "read_only": 0,
    "collapsible": 0,
    "allow_bulk_edit": 0,
    "ignore_user_permissions": 0,
    "allow_on_submit": 0,
    "report_hide": 0,
    "remember_last_selected_value": 0,
    "hide_border": 0,
    "in_filter": 0,
    "hide_seconds": 0,
    "hide_days": 0,
    "print_hide": 0,
    "print_hide_if_no_value": 0,
    "columns": 0,
    "is_custom_field": 1,
    "doctype": "Custom Field"    
},
   {
		"name": "Sales Invoice-info-trib",
		"parent": "Customize Form",
		"parentfield": "fields",
		"parenttype": "Customize Form",
		"idx": 10,
		"docstatus": 0,
		"label": "Informaci칩n Tributaria",
		"fieldtype": "Section Break",
		"fieldname": "sri-info-trib",		
		"in_preview": 0,
		"bold": 1,		
		"collapsible": 1
	},
  {
    "idx": 101,
    "name": "Purchase-Withholding-ambiente",
    "fieldname": "ambiente",
    "fieldtype": "Int",
    "label": "ambiente",   
    "reqd": 0,
    "in_list_view": 1,
    "read_only": 1
  },
  {
    "idx": 102,
    "name": "Purchase-Withholding-tipoEmision",
    "fieldname": "tipoEmision",
    "fieldtype": "Int",
    "label": "tipoEmision",   
    "reqd": 0,
    "in_list_view": 1,
    "read_only": 1
  },
  {
    "idx": 103,
    "name": "Purchase-Withholding-nombreComercial",
    "fieldname": "nombreComercial",
    "fieldtype": "Data",
    "label": "Nombre Comercial",   
    "reqd": 0,
    "in_list_view": 1,
    "read_only": 1
  },
  {
    "idx": 104,
    "name": "Purchase-Withholding-ruc",
    "fieldname": "ruc",
    "fieldtype": "Data",
    "label": "Ruc",   
    "reqd": 0,
    "in_list_view": 1,
    "read_only": 1
  },

  {
		"name": "Purchase-Withholding-column_break_001",
		"parent": "Customize Form",
		"parentfield": "fields",
		"parenttype": "Customize Form",
		"idx": 104,
		"docstatus": 0,
		"label": "",
		"fieldtype": "Column Break",
		"fieldname": "column_break_001",
		"is_custom_field": 1
	},
  {
    "idx": 105,
    "name": "Purchase-Withholding-codDoc",
    "fieldname": "codDoc",
    "fieldtype": "Data",
    "label": "codDoc",   
    "reqd": 0,
    "in_list_view": 1,
    "read_only": 1
  },

  {
    "idx": 106,
    "name": "Purchase-Withholding-secuencial",
    "fieldname": "secuencial",
    "fieldtype": "Int",
    "label": "secuencial",   
    "reqd": 0,
    "in_list_view": 1,
    "read_only": 1
  },

  {
    "idx": 107,
    "name": "Purchase-Withholding-dirMatriz",
    "fieldname": "dirMatriz",
    "fieldtype": "Data",
    "label": "dirMatriz",   
    "reqd": 0,
    "in_list_view": 1,
    "read_only": 1
  },

  {
    "idx": 108,
    "name": "Purchase-Withholding-agenteRetencion",
    "fieldname": "agenteRetencion",
    "fieldtype": "Int",
    "label": "agenteRetencion",   
    "reqd": 0,
    "in_list_view": 1,
    "read_only": 1
  },
  {
    "idx": 109,
    "name": "Purchase-Withholding-numeroAutorizacion",
    "fieldname": "numeroAutorizacion",
    "fieldtype": "Data",
    "label": "Numero Autorizacion",   
    "reqd": 0,
    "in_list_view": 1,
    "read_only": 1
  },
  {
    "idx": 110,
    "name": "Purchase-Withholding-numDoc",
    "fieldname": "numDoc",
    "fieldtype": "Data",
    "label": "Numero Documento",   
    "reqd": 0,
    "in_list_view": 1,
    "read_only": 1
  },
  
  

  
  {
      "name": "Purchase-Withholding-estab",
      "parent": "Customize Form",
      "parentfield": "fields",
      "parenttype": "Customize Form",
      "idx": 31,
      "docstatus": 0,
      "label": "estab",
      "fieldtype": "Link",		
      "fieldname": "estab",
      "non_negative": 0,
      "reqd": 0,
      "unique": 0,
      "in_list_view": 0,
      "in_standard_filter": 0,
      "in_global_search": 0,
      "in_preview": 0,
      "bold": 0,
      "allow_in_quick_entry": 0,
      "translatable": 1,
      "default": "001",
      "precision": "",
      "length": 0,
      "options": "Sri Establishment",
      "fetch_if_empty": 0,
      "permlevel": 0,
      "hidden": 0,
      "read_only": 0,
      "collapsible": 0,
      "allow_bulk_edit": 0,
      "ignore_user_permissions": 0,
      "allow_on_submit": 0,
      "report_hide": 0,
      "remember_last_selected_value": 0,
      "hide_border": 0,
      "in_filter": 0,
      "hide_seconds": 0,
      "hide_days": 0,
      "print_hide": 0,
      "print_hide_if_no_value": 0,
      "columns": 0,
      "is_custom_field": 1,
      "doctype": "Custom Field",
      "dt": "Sales Invoice"
  },
  {
      "name": "Purchase-Withholding-ptoemi",
      "parent": "Customize Form",
      "parentfield": "fields",
      "parenttype": "Customize Form",
      "idx": 32,
      "docstatus": 0,
      "label": "ptoEmi",
      "fieldtype": "Link",
      "fieldname": "ptoemi",
      "non_negative": 0,
      "reqd": 0,
      "unique": 0,
      "in_list_view": 0,
      "in_standard_filter": 0,
      "in_global_search": 0,
      "in_preview": 0,
      "bold": 0,
      "allow_in_quick_entry": 0,
      "translatable": 1,
      "default": "002",
      "precision": "",
      "length": 0,
      "options": "Sri Ptoemi",
      "fetch_if_empty": 0,
      "permlevel": 0,
      "hidden": 0,
      "read_only": 0,
      "collapsible": 0,
      "allow_bulk_edit": 0,
      "ignore_user_permissions": 0,
      "allow_on_submit": 0,
      "report_hide": 0,
      "remember_last_selected_value": 0,
      "hide_border": 0,
      "in_filter": 0,
      "hide_seconds": 0,
      "hide_days": 0,
      "print_hide": 0,
      "print_hide_if_no_value": 0,
      "columns": 0,
      "is_custom_field": 1,
      "doctype": "Custom Field",
      "dt": "Sales Invoice"
  },
  

{
  "name": "Sales Invoice-info-comp-withhold",
  "parent": "Customize Form",
  "parentfield": "fields",
  "parenttype": "Customize Form",
  "idx": 400,
  "docstatus": 0,
  "label": "Informaci칩n Compa침ia Retenci칩n",
  "fieldtype": "Section Break",
  "fieldname": "info-comp-withhold",		
  "in_preview": 0,
  "bold": 1,		
  "collapsible": 1
},
{
  "bold": 1,
  "default": "Now",
  "name": "Purchase-Withholding-fechaEmision",
  "fieldname": "fechaEmision",
  "fieldtype": "Datetime",
  "label": "fechaEmision",   
  "reqd": 1,
  "in_list_view": 1
},
{
  "idx": 402,
  "name": "Purchase-Withholding-identificacionSujetoRetenido",
  "fieldname": "identificacionSujetoRetenido",
  "fieldtype": "Data",
  "label": "identificacionSujetoRetenido",   
  "reqd": 0,
  "in_list_view": 1,
  "read_only": 1
},

{
  "idx": 403,
  "name": "Purchase-Withholding-tipoIdentificacionSujetoRetenido",
  "fieldname": "tipoIdentificacionSujetoRetenido",
  "fieldtype": "Data",
  "label": "tipoIdentificacionSujetoRetenido",   
  "reqd": 0,
  "in_list_view": 1,
  "read_only": 1
},
{
  "name": "Purchase-Withholding-column_break_002",
  "parent": "Customize Form",
  "parentfield": "fields",
  "parenttype": "Customize Form",
  "idx": 404,
  "docstatus": 0,
  "label": "",
  "fieldtype": "Column Break",
  "fieldname": "column_break_002",
  "is_custom_field": 1
},
{
  "idx": 404,
  "name": "Purchase-Withholding-razonSocialSujetoRetenido",
  "fieldname": "razonSocialSujetoRetenido",
  "fieldtype": "Data",
  "label": "razonSocialSujetoRetenido",   
  "reqd": 0,
  "in_list_view": 1,
  "read_only": 1
},
{
  "idx": 405,
  "name": "Purchase-Withholding-obligadoContabilidad",
  "fieldname": "obligadoContabilidad",
  "fieldtype": "Check",
  "label": "obligadoContabilidad",   
  "reqd": 0,
  "in_list_view": 1,
  "read_only": 1
},


{
  "idx": 406,
  "name": "Purchase-Withholding-periodoFiscal",
  "fieldname": "periodoFiscal",
  "fieldtype": "Data",
  "label": "periodoFiscal",   
  "reqd": 0,
  "in_list_view": 1,
  "read_only": 1
},
{
  "name": "Sales Invoice-withhold-section",
  "parent": "Customize Form",
  "parentfield": "fields",
  "parenttype": "Customize Form",
  "idx": 500,
  "docstatus": 0,
  "label": "Detalle Retenciones",
  "fieldtype": "Section Break",
  "fieldname": "withhold-section",		
  "in_preview": 0,
  "bold": 1,		
  "collapsible": 0
},
{
  "name": "Purchase-Withholding-taxes",
  "parent": "Customize Form",
  "parentfield": "fields",
  "parenttype": "Customize Form",
  "idx": 501,
  "docstatus": 0,
  "label": "Taxes",
  "fieldtype": "Table",
  "fieldname": "taxes",
  "non_negative": 0,
  "reqd": 0,
  "unique": 0,
  "in_list_view": 0,
  "in_standard_filter": 0,
  "in_global_search": 0,
  "in_preview": 0,
  "bold": 0,
  "allow_in_quick_entry": 0,
  "translatable": 1,
  "default": null,
  "precision": "",
  "length": 0,
  "options": "Purchase Taxes and Charges Ec",
  "fetch_if_empty": 0,
  "permlevel": 0,
  "hidden": 0,
  "read_only": 0,
  "collapsible": 0,
  "allow_bulk_edit": 0,
  "ignore_user_permissions": 0,
  "allow_on_submit": 0,
  "report_hide": 0,
  "remember_last_selected_value": 0,
  "hide_border": 0,
  "in_filter": 0,
  "hide_seconds": 0,
  "hide_days": 0,
  "print_hide": 0,
  "print_hide_if_no_value": 0,
  "columns": 0,
  "is_custom_field": 1
},
{
  "default": "Draft",
  "fieldname": "status",
  "fieldtype": "Select",
  "hide_days": 1,
  "hide_seconds": 1,
  "in_standard_filter": 1,
  "label": "Status",
  "length": 30,
  "no_copy": 1,
  "options": "\nDraft\nSubmitted\nPaid\nPartly Paid\nUnpaid\nUnpaid and Discounted\nPartly Paid and Discounted\nOverdue and Discounted\nOverdue\nCancelled",
  "print_hide": 1,
  "read_only": 1
 }
 ], 
 "links": [],
 "modified": "2024-01-14 10:04:36.618240",
 "modified_by": "Administrator",
 "module": "Erpnext Ec",
 "name": "Purchase Withholding Sri Ec",
 "owner": "Administrator",
 "permissions": [
    {
    "create": 1,
    "delete": 1,
    "email": 1,
    "export": 1,
    "print": 1,
    "read": 1,
    "report": 1,
    "role": "System Manager",
    "share": 1,
    "write": 1
    }
 ],
 "search_fields":"purchase_withholding_supplier",
 "sort_field": "modified",
 "sort_order": "DESC",
 "track_changes": 1
}
